behave_generator/.generator.py.swp
behave_generator/__init__.py
behave_generator/__main__.py
behave_generator/cli.py
behave_generator/generator.py
behave_generator/templates/browser.py
behave_generator/templates/environment_base.py
behave_generator-0.1.0.dist-info/DESCRIPTION.rst
behave_generator-0.1.0.dist-info/METADATA
behave_generator-0.1.0.dist-info/RECORD
behave_generator-0.1.0.dist-info/WHEEL
behave_generator-0.1.0.dist-info/entry_points.txt
behave_generator-0.1.0.dist-info/metadata.json
behave_generator-0.1.0.dist-info/top_level.txt
